[
    {
        "id": "a5d84b2c-9320-45b8-91c4-3c5dd45b533d",
        "x": 12,
        "y": 184,
        "width": 42,
        "height": 31,
        "dominant_color": [
            104.07080078125,
            80.625732421875,
            73.25634765625
        ]
    },
    {
        "id": "3e0049a5-fd01-44c1-8f60-29443b9266ef",
        "x": 14,
        "y": 72,
        "width": 30,
        "height": 26,
        "dominant_color": [
            95.98193359375,
            74.92578125,
            68.267822265625
        ]
    },
    {
        "id": "4ceef2a1-f743-418d-8d9a-ff5ec1d3952d",
        "x": 13,
        "y": 16,
        "width": 30,
        "height": 26,
        "dominant_color": [
            94.30712890625,
            72.559814453125,
            65.877197265625
        ]
    }
]