[
    {
        "id": "e7e6a86b-e8cf-4913-8e4d-14642f32b79a",
        "x": 511,
        "y": 301,
        "width": 71,
        "height": 11,
        "dominant_color": [
            195.30517578125,
            195.30517578125,
            195.30517578125
        ]
    },
    {
        "id": "78d9852a-9eab-4894-abfc-03ec66476a78",
        "x": 326,
        "y": 299,
        "width": 33,
        "height": 15,
        "dominant_color": [
            208.64208984375,
            208.64208984375,
            208.64208984375
        ]
    },
    {
        "id": "e3a96ecc-119d-4fb1-95bd-1632962ecef2",
        "x": 674,
        "y": 218,
        "width": 33,
        "height": 15,
        "dominant_color": [
            208.64208984375,
            208.64208984375,
            208.64208984375
        ]
    },
    {
        "id": "ed03dd53-6bf6-450d-b6be-96982f3f92a9",
        "x": 574,
        "y": 210,
        "width": 41,
        "height": 29,
        "dominant_color": [
            217.554443359375,
            201.093994140625,
            202.61181640625
        ]
    },
    {
        "id": "98708581-0738-42f9-9914-33eb1f53b9e8",
        "x": 264,
        "y": 205,
        "width": 36,
        "height": 29,
        "dominant_color": [
            213.838134765625,
            195.4873046875,
            196.43798828125
        ]
    },
    {
        "id": "77991f30-31e6-4932-a739-d433fe6b441e",
        "x": 445,
        "y": 198,
        "width": 16,
        "height": 33,
        "dominant_color": [
            226.4453125,
            198.671875,
            191.6279296875
        ]
    },
    {
        "id": "9bd9fd82-e131-49d6-8625-6479c95b5787",
        "x": 76,
        "y": 98,
        "width": 51,
        "height": 53,
        "dominant_color": [
            217.177978515625,
            203.848388671875,
            204.414794921875
        ]
    },
    {
        "id": "0242c9cc-ba79-46f8-809d-9fb76a023a6d",
        "x": 536,
        "y": 17,
        "width": 55,
        "height": 51,
        "dominant_color": [
            220.728515625,
            205.8564453125,
            207.8369140625
        ]
    },
    {
        "id": "9063c260-5083-482e-8d65-7afbeeb6149c",
        "x": 402,
        "y": 16,
        "width": 55,
        "height": 51,
        "dominant_color": [
            220.722412109375,
            206.005615234375,
            207.984130859375
        ]
    },
    {
        "id": "540b5566-832d-41ce-a711-3e1751626307",
        "x": 333,
        "y": 16,
        "width": 54,
        "height": 51,
        "dominant_color": [
            217.927490234375,
            200.5947265625,
            202.208984375
        ]
    }
]