[
    {
        "id": "21b6fc75-7ea7-403c-bf40-2324079d9aef",
        "x": 103,
        "y": 455,
        "width": 42,
        "height": 50,
        "dominant_color": [
            214.82470703125,
            193.3154296875,
            209.263671875
        ]
    },
    {
        "id": "f06c9435-e320-4216-8825-ee5eb8630470",
        "x": 94,
        "y": 375,
        "width": 53,
        "height": 51,
        "dominant_color": [
            215.81640625,
            205.375244140625,
            219.160400390625
        ]
    },
    {
        "id": "783e61a1-20d4-440d-9546-6a4f4df3473c",
        "x": 17,
        "y": 375,
        "width": 50,
        "height": 51,
        "dominant_color": [
            214.9765625,
            203.372314453125,
            217.736572265625
        ]
    },
    {
        "id": "18839468-eb33-4174-b3d7-22dc5288a7cf",
        "x": 92,
        "y": 290,
        "width": 57,
        "height": 47,
        "dominant_color": [
            205.663818359375,
            203.89453125,
            218.6572265625
        ]
    },
    {
        "id": "9fc350ce-1ad7-486c-90ba-96623d306260",
        "x": 12,
        "y": 289,
        "width": 57,
        "height": 50,
        "dominant_color": [
            207.033447265625,
            205.975830078125,
            220.45166015625
        ]
    },
    {
        "id": "817c226f-e8e9-4bd0-9df6-7a8bca4d027f",
        "x": 330,
        "y": 281,
        "width": 62,
        "height": 64,
        "dominant_color": [
            205.04248046875,
            203.556640625,
            217.34228515625
        ]
    },
    {
        "id": "3ca96612-1272-4f03-bf83-a6a239cc33d3",
        "x": 253,
        "y": 279,
        "width": 56,
        "height": 67,
        "dominant_color": [
            202.3525390625,
            200.660400390625,
            215.217529296875
        ]
    },
    {
        "id": "82a270bd-93d8-4747-955e-5cdf5c5e7d8f",
        "x": 17,
        "y": 184,
        "width": 50,
        "height": 51,
        "dominant_color": [
            214.9765625,
            203.372314453125,
            217.736572265625
        ]
    },
    {
        "id": "fb759308-a338-41e5-a46d-d4fce55f1c8f",
        "x": 421,
        "y": 183,
        "width": 50,
        "height": 51,
        "dominant_color": [
            214.9765625,
            203.372314453125,
            217.736572265625
        ]
    },
    {
        "id": "fa852b5a-76ee-4927-aeea-74d1ade49085",
        "x": 647,
        "y": 172,
        "width": 65,
        "height": 17,
        "dominant_color": [
            217.83740234375,
            217.83740234375,
            217.83740234375
        ]
    },
    {
        "id": "e885365d-565d-4a80-9b11-7436b2e7c7f0",
        "x": 508,
        "y": 166,
        "width": 57,
        "height": 17,
        "dominant_color": [
            207.6279296875,
            207.6279296875,
            207.6279296875
        ]
    },
    {
        "id": "90cdb9c1-3a8c-4965-aca7-716b80b115ba",
        "x": 335,
        "y": 105,
        "width": 52,
        "height": 47,
        "dominant_color": [
            198.8173828125,
            198.46044921875,
            214.634521484375
        ]
    },
    {
        "id": "b28c4c05-d941-442a-9d89-f44707e26a30",
        "x": 13,
        "y": 101,
        "width": 57,
        "height": 50,
        "dominant_color": [
            207.033447265625,
            205.975830078125,
            220.45166015625
        ]
    },
    {
        "id": "30a3bcba-5b71-4814-abaa-3a859a96967a",
        "x": 254,
        "y": 100,
        "width": 53,
        "height": 53,
        "dominant_color": [
            203.759521484375,
            204.0302734375,
            218.4833984375
        ]
    },
    {
        "id": "6a3d86c3-424e-4c0f-9f56-a18a4cb4c65a",
        "x": 93,
        "y": 100,
        "width": 57,
        "height": 52,
        "dominant_color": [
            201.627197265625,
            200.443603515625,
            216.4638671875
        ]
    },
    {
        "id": "a81acceb-b560-4393-93d4-e7eb14b772b7",
        "x": 173,
        "y": 99,
        "width": 57,
        "height": 54,
        "dominant_color": [
            203.927734375,
            202.220703125,
            217.703857421875
        ]
    },
    {
        "id": "b66152ef-80ea-45cb-b4c6-4616db00a877",
        "x": 412,
        "y": 98,
        "width": 58,
        "height": 49,
        "dominant_color": [
            207.915771484375,
            206.710205078125,
            221.00390625
        ]
    },
    {
        "id": "5278246f-5436-4821-b4e1-228cf42daa06",
        "x": 738,
        "y": 16,
        "width": 50,
        "height": 51,
        "dominant_color": [
            214.9765625,
            203.372314453125,
            217.736572265625
        ]
    },
    {
        "id": "e0908161-a20a-4486-8155-fd98a312dcc4",
        "x": 418,
        "y": 16,
        "width": 50,
        "height": 51,
        "dominant_color": [
            214.9765625,
            203.372314453125,
            217.736572265625
        ]
    },
    {
        "id": "982d19dd-6ada-4749-9628-2136619c872d",
        "x": 172,
        "y": 16,
        "width": 57,
        "height": 47,
        "dominant_color": [
            205.678955078125,
            203.900390625,
            218.6845703125
        ]
    },
    {
        "id": "be615e81-8788-490f-bcfd-45857df51f29",
        "x": 658,
        "y": 15,
        "width": 50,
        "height": 52,
        "dominant_color": [
            214.887939453125,
            203.8857421875,
            217.92724609375
        ]
    },
    {
        "id": "a7203965-c8c9-4a43-8c83-f60a2f6a512e",
        "x": 577,
        "y": 15,
        "width": 53,
        "height": 51,
        "dominant_color": [
            215.869140625,
            205.42724609375,
            219.209716796875
        ]
    },
    {
        "id": "5a4cf61b-9b37-4433-bf08-8a356f8faf59",
        "x": 498,
        "y": 15,
        "width": 50,
        "height": 52,
        "dominant_color": [
            214.887939453125,
            203.8857421875,
            217.92724609375
        ]
    },
    {
        "id": "b3571c62-7bcb-450a-a0f1-8c66fa4396fb",
        "x": 332,
        "y": 15,
        "width": 57,
        "height": 50,
        "dominant_color": [
            207.033447265625,
            205.975830078125,
            220.45166015625
        ]
    },
    {
        "id": "42ee6202-9abc-4875-8efc-47a1bed87787",
        "x": 252,
        "y": 15,
        "width": 57,
        "height": 49,
        "dominant_color": [
            206.26318359375,
            205.098876953125,
            219.607666015625
        ]
    },
    {
        "id": "d28cad83-f93d-4ba5-9607-bdea89dacad8",
        "x": 92,
        "y": 15,
        "width": 57,
        "height": 49,
        "dominant_color": [
            206.26318359375,
            205.098876953125,
            219.607666015625
        ]
    },
    {
        "id": "7f1419da-a2f4-41a1-9acd-f37d51aef2d2",
        "x": 12,
        "y": 15,
        "width": 57,
        "height": 50,
        "dominant_color": [
            207.033447265625,
            205.975830078125,
            220.45166015625
        ]
    }
]