[
    {
        "id": "e48a1eac-8505-4a2f-b878-de47104f5977",
        "x": 323,
        "y": 536,
        "width": 43,
        "height": 19,
        "dominant_color": [
            200.117919921875,
            129.677734375,
            218.39111328125
        ]
    },
    {
        "id": "08f68d46-9175-4d29-b17f-b1e9b267053c",
        "x": 432,
        "y": 324,
        "width": 42,
        "height": 16,
        "dominant_color": [
            195.177734375,
            117.71875,
            215.3291015625
        ]
    }
]