[
    {
        "id": "20512939-5db2-4eee-9b6f-2208cab7acd8",
        "x": 61,
        "y": 73,
        "width": 20,
        "height": 19,
        "dominant_color": [
            166.383544921875,
            135.463623046875,
            155.921142578125
        ]
    },
    {
        "id": "3c2a5a11-5527-4893-867d-67ae7a299e3f",
        "x": 262,
        "y": 70,
        "width": 20,
        "height": 19,
        "dominant_color": [
            165.9248046875,
            135.595947265625,
            156.85693359375
        ]
    },
    {
        "id": "750f5cf5-c0f3-495c-b422-3ce1ad58cadf",
        "x": 411,
        "y": 69,
        "width": 21,
        "height": 22,
        "dominant_color": [
            172.751953125,
            142.35693359375,
            162.123779296875
        ]
    },
    {
        "id": "1f9426c9-77c1-4686-a7f8-edae76eadc62",
        "x": 361,
        "y": 69,
        "width": 21,
        "height": 22,
        "dominant_color": [
            172.751953125,
            142.35693359375,
            162.123779296875
        ]
    },
    {
        "id": "48841ae0-4aa2-435b-96fe-9eca3fa1e5f3",
        "x": 311,
        "y": 69,
        "width": 21,
        "height": 22,
        "dominant_color": [
            172.751953125,
            142.35693359375,
            162.123779296875
        ]
    },
    {
        "id": "d53f3560-0ca0-4191-8d90-1756e1db6254",
        "x": 161,
        "y": 69,
        "width": 21,
        "height": 22,
        "dominant_color": [
            172.689453125,
            142.4072265625,
            162.00634765625
        ]
    },
    {
        "id": "60b5b576-325e-48f7-98c7-56e170a409fd",
        "x": 111,
        "y": 69,
        "width": 21,
        "height": 22,
        "dominant_color": [
            172.751953125,
            142.35693359375,
            162.123779296875
        ]
    },
    {
        "id": "a0db2652-c402-4413-88a7-090924ac1094",
        "x": 263,
        "y": 15,
        "width": 24,
        "height": 19,
        "dominant_color": [
            169.2138671875,
            136.961669921875,
            164.04052734375
        ]
    },
    {
        "id": "6a45b26b-f6ee-4452-aa50-d5744c10f91b",
        "x": 112,
        "y": 15,
        "width": 23,
        "height": 20,
        "dominant_color": [
            169.311767578125,
            136.73681640625,
            164.322265625
        ]
    },
    {
        "id": "c97b3f31-1abb-42c7-85a5-77e414a58aed",
        "x": 62,
        "y": 15,
        "width": 25,
        "height": 20,
        "dominant_color": [
            171.933837890625,
            140.298095703125,
            167.493896484375
        ]
    }
]