[
    {
        "id": "5fdfeca8-f8a1-44e6-9b36-ca837d58018d",
        "x": 399,
        "y": 1274,
        "width": 46,
        "height": 45,
        "dominant_color": [
            178.326171875,
            171.939208984375,
            165.64599609375
        ]
    },
    {
        "id": "3b61783a-c071-4458-8062-09e3877264d2",
        "x": 903,
        "y": 1098,
        "width": 36,
        "height": 41,
        "dominant_color": [
            170.494873046875,
            172.60595703125,
            171.837646484375
        ]
    },
    {
        "id": "d9dbf599-9ccd-422f-82f2-fab9e511f775",
        "x": 932,
        "y": 731,
        "width": 51,
        "height": 27,
        "dominant_color": [
            181.474365234375,
            164.73486328125,
            162.7587890625
        ]
    },
    {
        "id": "0158bd34-bcc5-458e-973d-d79b1473a1e1",
        "x": 1063,
        "y": 559,
        "width": 20,
        "height": 34,
        "dominant_color": [
            166.875,
            166.875,
            166.875
        ]
    },
    {
        "id": "f0732341-bffc-476e-bce1-4f4316127cbe",
        "x": 924,
        "y": 499,
        "width": 79,
        "height": 98,
        "dominant_color": [
            180.1533203125,
            172.76904296875,
            170.884033203125
        ]
    },
    {
        "id": "d262b8b9-39f8-43b1-8aac-c1fd73dec74a",
        "x": 26,
        "y": 498,
        "width": 55,
        "height": 96,
        "dominant_color": [
            170.12939453125,
            160.95849609375,
            156.798583984375
        ]
    },
    {
        "id": "fd4ac402-28d3-4245-94d7-11fcaa03f707",
        "x": 276,
        "y": 362,
        "width": 63,
        "height": 78,
        "dominant_color": [
            164.67138671875,
            166.489990234375,
            160.47119140625
        ]
    },
    {
        "id": "33cc5538-ad30-4442-951a-eef25ed874a0",
        "x": 811,
        "y": 333,
        "width": 40,
        "height": 38,
        "dominant_color": [
            165.911376953125,
            157.824462890625,
            156.937744140625
        ]
    },
    {
        "id": "42fc49fb-75aa-4cf1-a7c3-3f1b4b9964ba",
        "x": 681,
        "y": 333,
        "width": 40,
        "height": 38,
        "dominant_color": [
            165.854736328125,
            157.750732421875,
            156.861328125
        ]
    },
    {
        "id": "688ced32-2a2f-4142-b531-b54d0fba5792",
        "x": 551,
        "y": 332,
        "width": 58,
        "height": 86,
        "dominant_color": [
            173.505615234375,
            172.41552734375,
            168.04248046875
        ]
    },
    {
        "id": "54b830da-8438-47c2-8eff-0cc15d035a49",
        "x": 413,
        "y": 332,
        "width": 51,
        "height": 104,
        "dominant_color": [
            160.02880859375,
            161.529296875,
            155.3544921875
        ]
    },
    {
        "id": "2e2d0569-1be5-468c-8b30-69b9991a2c26",
        "x": 291,
        "y": 332,
        "width": 40,
        "height": 38,
        "dominant_color": [
            165.260986328125,
            157.068359375,
            156.38818359375
        ]
    },
    {
        "id": "bd62bf7a-7441-417c-ad8f-470fa29a3528",
        "x": 162,
        "y": 331,
        "width": 41,
        "height": 38,
        "dominant_color": [
            166.948974609375,
            158.831787109375,
            158.114013671875
        ]
    },
    {
        "id": "ead7ba0f-4161-4550-a677-456e44297d5b",
        "x": 932,
        "y": 236,
        "width": 20,
        "height": 34,
        "dominant_color": [
            166.875,
            166.875,
            166.875
        ]
    },
    {
        "id": "26e3d80f-e621-4bd5-91ae-5b533e310ac9",
        "x": 28,
        "y": 178,
        "width": 55,
        "height": 107,
        "dominant_color": [
            178.301513671875,
            168.953369140625,
            164.564208984375
        ]
    },
    {
        "id": "8a9fb744-bafa-47ec-9e7b-785058f7cd87",
        "x": 809,
        "y": 177,
        "width": 53,
        "height": 66,
        "dominant_color": [
            180.192626953125,
            170.520751953125,
            165.439208984375
        ]
    },
    {
        "id": "9e976f01-4018-46f4-9468-6c41e6ee3edb",
        "x": 679,
        "y": 177,
        "width": 52,
        "height": 72,
        "dominant_color": [
            177.0439453125,
            167.284423828125,
            162.154052734375
        ]
    },
    {
        "id": "66f6b080-1ed6-411a-9e3d-2438f5763da5",
        "x": 420,
        "y": 177,
        "width": 53,
        "height": 73,
        "dominant_color": [
            177.4736328125,
            168.011962890625,
            164.099609375
        ]
    },
    {
        "id": "ed30908a-75af-4f91-9ed8-2e8df2bb1e3e",
        "x": 415,
        "y": 48,
        "width": 38,
        "height": 83,
        "dominant_color": [
            174.374755859375,
            161.44921875,
            153.60693359375
        ]
    },
    {
        "id": "1541d091-a47c-4c9d-9929-f65232448676",
        "x": 285,
        "y": 47,
        "width": 46,
        "height": 85,
        "dominant_color": [
            169.021728515625,
            154.3740234375,
            147.960205078125
        ]
    },
    {
        "id": "466550e1-e6a7-4502-b233-dec13f06e443",
        "x": 947,
        "y": 22,
        "width": 55,
        "height": 108,
        "dominant_color": [
            164.43115234375,
            164.935302734375,
            161.903564453125
        ]
    },
    {
        "id": "c0f2228b-d183-4c73-848e-cc8cef205f0f",
        "x": 817,
        "y": 22,
        "width": 54,
        "height": 109,
        "dominant_color": [
            163.296875,
            164.325927734375,
            160.6708984375
        ]
    },
    {
        "id": "3825e990-2bad-40af-95e9-c4c49a04d4e6",
        "x": 687,
        "y": 22,
        "width": 55,
        "height": 109,
        "dominant_color": [
            164.1494140625,
            164.8681640625,
            161.793701171875
        ]
    }
]